{
  "version": "5.5.0",
  "flags": {},
  "shapes": [
    {
      "label": "l_line",
      "points": [
        [
          430.6666666666667,
          569.3333333333334
        ],
        [
          313.3333333333333,
          570.6666666666666
        ],
        [
          312.0,
          668.0
        ]
      ],
      "group_id": null,
      "description": "",
      "shape_type": "linestrip",
      "flags": {},
      "mask": null
    },
    {
      "label": "l_line",
      "points": [
        [
          570.6666666666666,
          569.3333333333334
        ],
        [
          456.0,
          569.3333333333334
        ],
        [
          456.0,
          701.3333333333334
        ]
      ],
      "group_id": null,
      "description": "",
      "shape_type": "linestrip",
      "flags": {},
      "mask": null
    },
    {
      "label": "l_line",
      "points": [
        [
          697.3333333333334,
          569.3333333333334
        ],
        [
          585.3333333333334,
          570.6666666666666
        ],
        [
          586.6666666666666,
          680.0
        ],
        [
          88.0,
          681.3333333333334
        ]
      ],
      "group_id": null,
      "description": "",
      "shape_type": "linestrip",
      "flags": {},
      "mask": null
    },
    {
      "label": "l_line",
      "points": [
        [
          900.0,
          569.3333333333334
        ],
        [
          786.6666666666666,
          570.6666666666666
        ],
        [
          785.3333333333334,
          666.6666666666666
        ]
      ],
      "group_id": null,
      "description": "",
      "shape_type": "linestrip",
      "flags": {},
      "mask": null
    },
    {
      "label": "l_line",
      "points": [
        [
          1162.6666666666667,
          569.3333333333334
        ],
        [
          1046.6666666666667,
          568.0
        ],
        [
          1048.0,
          702.6666666666666
        ]
      ],
      "group_id": null,
      "description": "",
      "shape_type": "linestrip",
      "flags": {},
      "mask": null
    },
    {
      "label": "l_line",
      "points": [
        [
          1444.0,
          568.0
        ],
        [
          1329.3333333333333,
          569.3333333333334
        ],
        [
          1330.6666666666667,
          1004.0
        ]
      ],
      "group_id": null,
      "description": "",
      "shape_type": "linestrip",
      "flags": {},
      "mask": null
    },
    {
      "label": "l_line",
      "points": [
        [
          1588.0,
          569.3333333333334
        ],
        [
          1472.0,
          569.3333333333334
        ],
        [
          1470.6666666666667,
          1026.6666666666667
        ]
      ],
      "group_id": null,
      "description": "",
      "shape_type": "linestrip",
      "flags": {},
      "mask": null
    },
    {
      "label": "l_line",
      "points": [
        [
          1929.3333333333333,
          569.3333333333334
        ],
        [
          1814.6666666666667,
          569.3333333333334
        ],
        [
          1814.6666666666667,
          670.6666666666666
        ]
      ],
      "group_id": null,
      "description": "",
      "shape_type": "linestrip",
      "flags": {},
      "mask": null
    },
    {
      "label": "l_line",
      "points": [
        [
          2042.6666666666667,
          569.3333333333334
        ],
        [
          1980.0,
          568.0
        ],
        [
          1980.0,
          701.3333333333334
        ]
      ],
      "group_id": null,
      "description": "",
      "shape_type": "linestrip",
      "flags": {},
      "mask": null
    },
    {
      "label": "l_line",
      "points": [
        [
          1656.0,
          1234.6666666666667
        ],
        [
          1545.3333333333333,
          1232.0
        ],
        [
          1541.3333333333333,
          1112.0
        ]
      ],
      "group_id": null,
      "description": "",
      "shape_type": "linestrip",
      "flags": {},
      "mask": null
    },
    {
      "label": "l_line",
      "points": [
        [
          1512.0,
          1226.6666666666667
        ],
        [
          1402.6666666666667,
          1225.3333333333333
        ],
        [
          1400.0,
          1036.0
        ]
      ],
      "group_id": null,
      "description": "",
      "shape_type": "linestrip",
      "flags": {},
      "mask": null
    },
    {
      "label": "l_line",
      "points": [
        [
          1137.3333333333333,
          1214.6666666666667
        ],
        [
          1020.0,
          1212.0
        ],
        [
          1021.3333333333334,
          1093.3333333333333
        ]
      ],
      "group_id": null,
      "description": "",
      "shape_type": "linestrip",
      "flags": {},
      "mask": null
    },
    {
      "label": "l_line",
      "points": [
        [
          1018.6666666666666,
          1257.3333333333333
        ],
        [
          905.3333333333334,
          1257.3333333333333
        ],
        [
          902.6666666666666,
          1021.3333333333334
        ]
      ],
      "group_id": null,
      "description": "",
      "shape_type": "linestrip",
      "flags": {},
      "mask": null
    },
    {
      "label": "l_line",
      "points": [
        [
          889.3333333333334,
          1208.0
        ],
        [
          773.3333333333334,
          1208.0
        ],
        [
          773.3333333333334,
          1086.6666666666667
        ]
      ],
      "group_id": null,
      "description": "",
      "shape_type": "linestrip",
      "flags": {},
      "mask": null
    },
    {
      "label": "l_line",
      "points": [
        [
          642.6666666666666,
          1205.3333333333333
        ],
        [
          524.0,
          1202.6666666666667
        ],
        [
          526.6666666666666,
          1086.6666666666667
        ]
      ],
      "group_id": null,
      "description": "",
      "shape_type": "linestrip",
      "flags": {},
      "mask": null
    },
    {
      "label": "l_line",
      "points": [
        [
          509.3333333333333,
          1252.0
        ],
        [
          394.6666666666667,
          1252.0
        ],
        [
          397.3333333333333,
          1014.6666666666666
        ]
      ],
      "group_id": null,
      "description": "",
      "shape_type": "linestrip",
      "flags": {},
      "mask": null
    },
    {
      "label": "symbol",
      "points": [
        [
          311.6470588235294,
          512.8235294117648
        ],
        [
          369.29411764705884,
          568.1176470588235
        ]
      ],
      "group_id": null,
      "description": "",
      "shape_type": "rectangle",
      "flags": {},
      "mask": null
    },
    {
      "label": "symbol",
      "points": [
        [
          451.6470588235294,
          518.7058823529412
        ],
        [
          509.29411764705884,
          570.4705882352941
        ]
      ],
      "group_id": null,
      "description": "",
      "shape_type": "rectangle",
      "flags": {},
      "mask": null
    },
    {
      "label": "symbol",
      "points": [
        [
          582.2352941176471,
          516.3529411764706
        ],
        [
          642.2352941176471,
          570.4705882352941
        ]
      ],
      "group_id": null,
      "description": "",
      "shape_type": "rectangle",
      "flags": {},
      "mask": null
    },
    {
      "label": "symbol",
      "points": [
        [
          785.7647058823529,
          516.3529411764706
        ],
        [
          837.5294117647059,
          569.2941176470588
        ]
      ],
      "group_id": null,
      "description": "",
      "shape_type": "rectangle",
      "flags": {},
      "mask": null
    },
    {
      "label": "symbol",
      "points": [
        [
          1039.8823529411764,
          516.3529411764706
        ],
        [
          1103.4117647058822,
          569.2941176470588
        ]
      ],
      "group_id": null,
      "description": "",
      "shape_type": "rectangle",
      "flags": {},
      "mask": null
    },
    {
      "label": "symbol",
      "points": [
        [
          1322.235294117647,
          516.3529411764706
        ],
        [
          1385.764705882353,
          568.1176470588235
        ]
      ],
      "group_id": null,
      "description": "",
      "shape_type": "rectangle",
      "flags": {},
      "mask": null
    },
    {
      "label": "symbol",
      "points": [
        [
          1461.0588235294117,
          515.1764705882352
        ],
        [
          1525.764705882353,
          570.4705882352941
        ]
      ],
      "group_id": null,
      "description": "",
      "shape_type": "rectangle",
      "flags": {},
      "mask": null
    },
    {
      "label": "symbol",
      "points": [
        [
          1810.4705882352941,
          521.0588235294118
        ],
        [
          1868.1176470588234,
          571.6470588235294
        ]
      ],
      "group_id": null,
      "description": "",
      "shape_type": "rectangle",
      "flags": {},
      "mask": null
    },
    {
      "label": "symbol",
      "points": [
        [
          1972.8235294117646,
          515.1764705882352
        ],
        [
          2035.1764705882351,
          570.4705882352941
        ]
      ],
      "group_id": null,
      "description": "",
      "shape_type": "rectangle",
      "flags": {},
      "mask": null
    },
    {
      "label": "symbol",
      "points": [
        [
          1544.5882352941176,
          1179.8823529411764
        ],
        [
          1598.705882352941,
          1235.1764705882351
        ]
      ],
      "group_id": null,
      "description": "",
      "shape_type": "rectangle",
      "flags": {},
      "mask": null
    },
    {
      "label": "symbol",
      "points": [
        [
          1398.705882352941,
          1177.5294117647059
        ],
        [
          1454.0,
          1222.235294117647
        ]
      ],
      "group_id": null,
      "description": "",
      "shape_type": "rectangle",
      "flags": {},
      "mask": null
    },
    {
      "label": "symbol",
      "points": [
        [
          1024.5882352941176,
          1165.764705882353
        ],
        [
          1076.3529411764705,
          1216.3529411764705
        ]
      ],
      "group_id": null,
      "description": "",
      "shape_type": "rectangle",
      "flags": {},
      "mask": null
    },
    {
      "label": "symbol",
      "points": [
        [
          902.2352941176471,
          1206.941176470588
        ],
        [
          962.2352941176471,
          1259.8823529411764
        ]
      ],
      "group_id": null,
      "description": "",
      "shape_type": "rectangle",
      "flags": {},
      "mask": null
    },
    {
      "label": "symbol",
      "points": [
        [
          776.3529411764706,
          1157.5294117647059
        ],
        [
          830.4705882352941,
          1208.1176470588234
        ]
      ],
      "group_id": null,
      "description": "",
      "shape_type": "rectangle",
      "flags": {},
      "mask": null
    },
    {
      "label": "symbol",
      "points": [
        [
          525.7647058823529,
          1156.3529411764705
        ],
        [
          584.5882352941177,
          1203.4117647058822
        ]
      ],
      "group_id": null,
      "description": "",
      "shape_type": "rectangle",
      "flags": {},
      "mask": null
    },
    {
      "label": "symbol",
      "points": [
        [
          392.8235294117647,
          1201.0588235294117
        ],
        [
          454.0,
          1255.1764705882351
        ]
      ],
      "group_id": null,
      "description": "",
      "shape_type": "rectangle",
      "flags": {},
      "mask": null
    }
  ],
  "imagePath": "page-04_r1c0.png",
  "imageData": null,
  "imageHeight": 2048,
  "imageWidth": 2048
}